{
  "request_id": "61ac0a51-a26b-4957-bfd3-4db1c78a6a96",
  "code": 0,
  "data": {
    "fields": [
      "trade_date",
      "exchange_id",
      "rzye",
      "rzmre",
      "rzche",
      "rqye",
      "rqmcl",
      "rzrqye",
      "rqyl"
    ],
    "items": [
      [
        "20220615",
        "SSE",
        793609922510.0,
        60233212499.0,
        57206039073.0,
        53630674633.0,
        536441330.0,
        847240597143.0,
        6806672978.0
      ],
      [
        "20220615",
        "SZSE",
        681814025381.0,
        49656427190.0,
        47707924103.0,
        24426319577.0,
        173427533.0,
        706240344958.0,
        1807959729.0
      ]
    ],
    "has_more": false,
    "count": -1
  },
  "msg": ""
}